rdf_crawler.py
rdf_service.py
setup.cfg
setup.py
RDFCrawler.egg-info/PKG-INFO
RDFCrawler.egg-info/SOURCES.txt
RDFCrawler.egg-info/dependency_links.txt
RDFCrawler.egg-info/top_level.txt