Metadata-Version: 1.1
Name: RDFCrawler
Version: 1.4.3
Summary: A RESTful services for Python that explores and replicates a RDF topology.
Home-page: https://github.com/ignaciomolina/RDFCrawler
Author: Ignacio Molina Cuquerella
Author-email: imolina@centeropenmiddleware.com
License: UNKNOWN
Download-URL: https://github.com/ignaciomolina/RDFCrawler/tarball/1.4.3
Platform: UNKNOWN
Requires: flask
Requires: rdflib
